mcp_sql_helper/__init__.py
mcp_sql_helper/__main__.py
mcp_sql_helper/server.py
mcp_sql_helper-0.1.2.dist-info/METADATA
mcp_sql_helper-0.1.2.dist-info/WHEEL
mcp_sql_helper-0.1.2.dist-info/top_level.txt
mcp_sql_helper-0.1.2.dist-info/RECORD
